{
    "xsando04": {
        "time_spent_thresholded_(h)": 0.8997277777777778,
        "time_spent_(h)": 0.8997277777777778,
        "mean_time_per_query(min)": 4.152589743589743,
        "time_spent_query_quartile1": 162.737,
        "time_spent_query_quartile2": 228.332,
        "time_spent_query_quartile3": 328.74,
        "mean_time_per_card(s)": 20.59940322580645,
        "mean_asymmetric_query_length": 18.153846153846153,
        "mean_symmetric_query_length": null,
        "total_queries": 13,
        "total_asymmetric_queries": 13,
        "total_symmetric_queries": 0,
        "mean_#cards_per_query": 9.538461538461538,
        "total_cards": 124,
        "total_relevant_cards": 65,
        "total_irrelevant_cards": 59,
        "mean_length_of_annotated_documents": 92.16935483870968,
        "name": "xsando04",
        "email": "xsando04@stud.fit.vutbr.cz"
    },
    "xsajko01": {
        "time_spent_thresholded_(h)": 6.00504888888889,
        "time_spent_(h)": 6.00504888888889,
        "mean_time_per_query(min)": 5.074689201877935,
        "time_spent_query_quartile1": 182.0485,
        "time_spent_query_quartile2": 286.006,
        "time_spent_query_quartile3": 382.4175,
        "mean_time_per_card(s)": 30.612541009463726,
        "mean_asymmetric_query_length": 17.452380952380953,
        "mean_symmetric_query_length": 68.10344827586206,
        "total_queries": 71,
        "total_asymmetric_queries": 42,
        "total_symmetric_queries": 29,
        "mean_#cards_per_query": 8.929577464788732,
        "total_cards": 634,
        "total_relevant_cards": 359,
        "total_irrelevant_cards": 275,
        "mean_length_of_annotated_documents": 89.99526813880126,
        "name": "xsajko01",
        "email": "xsajko01@stud.fit.vutbr.cz"
    },
    "petr.janicek": {
        "time_spent_thresholded_(h)": 0.5499138888888891,
        "time_spent_(h)": 0.5499138888888891,
        "mean_time_per_query(min)": 1.0998277777777783,
        "time_spent_query_quartile1": 31.95375,
        "time_spent_query_quartile2": 50.382000000000005,
        "time_spent_query_quartile3": 80.219,
        "mean_time_per_card(s)": 7.177073333333334,
        "mean_asymmetric_query_length": 18.1,
        "mean_symmetric_query_length": 36.7,
        "total_queries": 30,
        "total_asymmetric_queries": 20,
        "total_symmetric_queries": 10,
        "mean_#cards_per_query": 5.0,
        "total_cards": 150,
        "total_relevant_cards": 110,
        "total_irrelevant_cards": 40,
        "mean_length_of_annotated_documents": 66.08666666666667,
        "name": "petr.janicek",
        "email": "548646@mail.muni.cz"
    }
}